eunomia/__init__.py
eunomia/cli.py
eunomia/config.py
eunomia/api/__init__.py
eunomia/api/dependencies.py
eunomia/api/main.py
eunomia/api/routers.py
eunomia/engine/__init__.py
eunomia/engine/engine.py
eunomia/engine/evaluator.py
eunomia/engine/router.py
eunomia/engine/utils.py
eunomia/engine/db/__init__.py
eunomia/engine/db/crud.py
eunomia/engine/db/db.py
eunomia/engine/db/models.py
eunomia/fetchers/__init__.py
eunomia/fetchers/base.py
eunomia/fetchers/factory.py
eunomia/fetchers/passport/__init__.py
eunomia/fetchers/passport/main.py
eunomia/fetchers/passport/router.py
eunomia/fetchers/registry/__init__.py
eunomia/fetchers/registry/main.py
eunomia/fetchers/registry/router.py
eunomia/fetchers/registry/db/__init__.py
eunomia/fetchers/registry/db/crud.py
eunomia/fetchers/registry/db/db.py
eunomia/fetchers/registry/db/models.py
eunomia/server/__init__.py
eunomia/server/main.py
eunomia/server/router.py
eunomia/utils/__init__.py
eunomia/utils/batch_processor.py
eunomia_ai-0.3.10.dist-info/METADATA
eunomia_ai-0.3.10.dist-info/WHEEL
eunomia_ai-0.3.10.dist-info/entry_points.txt
eunomia_ai-0.3.10.dist-info/licenses/LICENSE
eunomia_ai-0.3.10.dist-info/RECORD
