Metadata-Version: 2.4
Name: eunomia-ai
Version: 0.3.10
Summary: Authorization layer for AI Agents
Author-email: What About You team <info@whataboutyou.ai>
License-Expression: Apache-2.0
License-File: LICENSE
Requires-Python: >=3.10
Requires-Dist: eunomia-core>=0.3.10
Requires-Dist: fastapi[standard]>=0.115.9
Requires-Dist: httpx>=0.28.1
Requires-Dist: pydantic-settings>=2.8.1
Requires-Dist: python-jose>=3.5.0
Requires-Dist: sqlalchemy>=2.0.38
